{
  "start": {
    "1": "Привет, {}",
    "2": "Регистрация успешно пройдена",
    "3": "Ты находишься в боте, который тебе поможет разобраться в расписании и не пропустить пары.\nДля этого напиши мне, в каком курсе ты учишься",
    "4": "Отлично! Осталось совсем немного.\nНапиши теперь мне свою группу",
    "5": "Также мне нужно знать в какой ты подгруппе\nНапишите 1 или 2",
    "6": "Нужно вводить число от 1 до 4",
    "7": "Нужно вводить число от 1 до 16",
    "8": "Подгрупп может быть только 2",
    "9": "Поздравляем! Ты прошел регистрацию, теперь можешь пользоваться ботом полноценно.\n\nЧтобы знать какие функции доступны - напиши команду /help"
  }
}